{"CompraManha": 12.19, "VendaManha": 12.27, "PUCompraManha": 4232.37, "PUVendaManha": 4227.16, "PUBaseManha": 4229.76, "Data_Vencimento": 1988150400000, "Data_Base": 1779667200000, "Tipo": "Tesouro Prefixado com Juros Semestrais 2033", "dt_update": 1793577600000}
{"CompraManha": 12.3, "VendaManha": 12.34, "PUCompraManha": 4225.11, "PUVendaManha": 4218.39, "PUBaseManha": 4221.75, "Data_Vencimento": 1988150400000, "Data_Base": 1779408000000, "Tipo": "Tesouro Prefixado com Juros Semestrais 2033", "dt_update": 1793318400000}
